MANIFEST.in
setup.py
ursa2/__init__.py
ursa2/build.py
ursa2/conf.py
ursa2/deps.py
ursa2/exception.py
ursa2/handler.py
ursa2/http.py
ursa2/log.py
ursa2/main.py
ursa2/proxy.py
ursa2/render.py
ursa2/replace.py
ursa2/route.py
ursa2/server.py
ursa2/timestamp.py
ursa2/utils.py
ursa2.egg-info/PKG-INFO
ursa2.egg-info/SOURCES.txt
ursa2.egg-info/dependency_links.txt
ursa2.egg-info/entry_points.txt
ursa2.egg-info/requires.txt
ursa2.egg-info/top_level.txt
ursa2/assets/certificate.pem
ursa2/assets/privatekey.pem
ursa2/assets/r.js
ursa2/assets/rpl.js
ursa2/assets/yuicompressor-2.4.8.jar
ursa2/assets/clo/manifest.json
ursa2/assets/clo/_data/_ursa.json
ursa2/assets/clo/_data/index.json
ursa2/assets/clo/static/css/font.css
ursa2/assets/clo/static/css/grid.css
ursa2/assets/clo/static/css/main.css
ursa2/assets/clo/static/css/page.css
ursa2/assets/clo/static/css/reset.css
ursa2/assets/clo/static/img/p.gif
ursa2/assets/clo/static/js/main.js
ursa2/assets/clo/static/js/text.js
ursa2/assets/clo/template/index.tpl
ursa2/assets/clo/template/parent.tpl
ursa2/tpl/header.html
ursa2/tpl/help.html
ursa2/tpl/index.html
ursa2/tpl/json.html
ursa2/tpl/mgr.html
ursa2/tpl/parent.html
ursa2/tpl/static.html
ursa2/tpl/subparent.tpl