Metadata-Version: 1.0
Name: ursa2
Version: 0.0.12
Summary: Ursa2 is an enhanced version of ursa which is a powerful front web developing environment.
Home-page: https://github.com/yanni4night/ursa2
Author: Yanni Nightingale
Author-email: yanni4night@gmail.com
License: MIT
Keywords: ursa,fe,develop,web,jinja2,build
Platform: UNKNOWN
